asyncio_for_robotics/__init__.py
asyncio_for_robotics/py.typed
asyncio_for_robotics/core/__init__.py
asyncio_for_robotics/core/_logger.py
asyncio_for_robotics/core/sub.py
asyncio_for_robotics/core/utils.py
asyncio_for_robotics/example/__init__.py
asyncio_for_robotics/example/custom_stdout.py
asyncio_for_robotics/example/python_discussion.py
asyncio_for_robotics/example/ros2_discussion.py
asyncio_for_robotics/example/ros2_double_listener.py
asyncio_for_robotics/example/ros2_double_talker.py
asyncio_for_robotics/example/ros2_event_callback.py
asyncio_for_robotics/example/ros2_listener.py
asyncio_for_robotics/example/ros2_pubsub.py
asyncio_for_robotics/example/ros2_service_client.py
asyncio_for_robotics/example/ros2_service_server.py
asyncio_for_robotics/example/ros2_talker.py
asyncio_for_robotics/example/zenoh_discussion.py
asyncio_for_robotics/ros2/__init__.py
asyncio_for_robotics/ros2/future.py
asyncio_for_robotics/ros2/service.py
asyncio_for_robotics/ros2/session.py
asyncio_for_robotics/ros2/sub.py
asyncio_for_robotics/ros2/utils.py
asyncio_for_robotics/textio/__init__.py
asyncio_for_robotics/textio/sub.py
asyncio_for_robotics/zenoh/__init__.py
asyncio_for_robotics/zenoh/session.py
asyncio_for_robotics/zenoh/sub.py
asyncio_for_robotics-1.2.6.dist-info/licenses/LICENSE
asyncio_for_robotics-1.2.6.dist-info/METADATA
asyncio_for_robotics-1.2.6.dist-info/WHEEL
asyncio_for_robotics-1.2.6.dist-info/top_level.txt
asyncio_for_robotics-1.2.6.dist-info/RECORD
