Metadata-Version: 2.4
Name: asyncio_for_robotics
Version: 1.2.6
Summary: Asyncio interface for ROS 2, Zenoh, and other robotic middlewares.
Author-email: Elian NEPPEL <elian.dev@posteo.com>
License-Expression: MIT
Project-URL: Homepage, https://github.com/2lian/asyncio-for-robotics
Project-URL: Repository, https://github.com/2lian/asyncio-for-robotics
Project-URL: Issues, https://github.com/2lian/asyncio-for-robotics/issues
Keywords: asyncio,robotics,ros2,zenoh,publisher,subscriber
Classifier: Development Status :: 4 - Beta
Classifier: Intended Audience :: Science/Research
Classifier: Intended Audience :: Developers
Classifier: Natural Language :: English
Classifier: Environment :: Console
Classifier: Programming Language :: Python :: 3 :: Only
Classifier: Programming Language :: Python :: 3.10
Classifier: Programming Language :: Python :: 3.11
Classifier: Programming Language :: Python :: 3.12
Classifier: Programming Language :: Python :: 3.13
Classifier: Programming Language :: Python :: 3.14
Classifier: Operating System :: POSIX :: Linux
Classifier: Operating System :: Microsoft :: Windows
Classifier: Operating System :: MacOS
Classifier: Topic :: Scientific/Engineering
Classifier: Topic :: Software Development :: Embedded Systems
Classifier: Topic :: System :: Networking
Classifier: Framework :: AsyncIO
Requires-Python: <3.15,>=3.10
License-File: LICENSE
Requires-Dist: typing_extensions>=4.0; python_version < "3.11"
Requires-Dist: async-timeout; python_version < "3.11"
Provides-Extra: zenoh
Requires-Dist: eclipse-zenoh>=1.0.0; extra == "zenoh"
Provides-Extra: dev
Requires-Dist: colorama; extra == "dev"
Requires-Dist: pytest; extra == "dev"
Requires-Dist: pytest-asyncio; extra == "dev"
Provides-Extra: benchmarks
Requires-Dist: pyfiglet; extra == "benchmarks"
Requires-Dist: uvloop; extra == "benchmarks"
Provides-Extra: build
Requires-Dist: build; extra == "build"
Requires-Dist: twine; extra == "build"
Dynamic: license-file
